pycodegrade/__init__.py
pycodegrade/function_test.py
pycodegrade/functiontest.py
pycodegrade/grader.py
pycodegrade/sample.py
pycodegrade/utils.py
pycodegrade-0.0.9.dist-info/METADATA
pycodegrade-0.0.9.dist-info/WHEEL
pycodegrade-0.0.9.dist-info/top_level.txt
pycodegrade-0.0.9.dist-info/RECORD
